{
  "config": {
    "batch_size": 32,
    "group_size": 4,
    "group_weight": 1.0,
    "hard_weight": 0.5,
    "learning_rate": 2e-05,
    "margin": 0.5,
    "model_name": "sentence-transformers/paraphrase-MiniLM-L3-v2",
    "normalize_embeddings": true,
    "objectives": [
      "triplet",
      "group",
      "hybrid",
      "hybrid_xbm",
      "hybrid_radius",
      "all"
    ],
    "radius_weight": 0.05,
    "seed": 0,
    "spread_weight": 0.1,
    "test_size": 0.25,
    "train_steps": 80,
    "triplet_weight": 1.0,
    "variance_weight": 0.05,
    "xbm_size": 256,
    "xbm_weight": 0.25
  },
  "examples": 256,
  "group_triplets": 48,
  "methods": {
    "all_finetuned:sentence-transformers/paraphrase-MiniLM-L3-v2": {
      "dimensions": 384,
      "group_loss": 0.5975976796435766,
      "initial_group_loss": 1.0122567041741284,
      "initial_probe": {
        "accuracy": 0.78125,
        "confusion_matrix": [
          [
            25,
            7
          ],
          [
            7,
            25
          ]
        ],
        "macro_f1": 0.78125,
        "train_accuracy": 0.875,
        "train_macro_f1": 0.8749864351600651
      },
      "initial_retrieval": {
        "map_at_r": 0.30303404557635916,
        "mean_relevant_items": 96.0,
        "precision_at_1": 0.546875
      },
      "initial_space": {
        "drift_to_gap_ratio": 0.837125212693542,
        "signal_to_noise_ratio": 0.11641856857046612,
        "test_within_class_radius": 0.8372645325001753,
        "train_centroid_gap": 0.19390105222162995,
        "train_test_centroid_drift": 0.16231945958253358,
        "train_within_class_radius": 0.8282863723304836
      },
      "initial_triplet_loss": 0.4912109756862438,
      "objective_history": [
        1.4962036609649658,
        1.466300129890442,
        1.532179355621338,
        1.5194908380508423,
        1.5716099739074707,
        1.512452483177185,
        1.437990665435791,
        1.4735653400421143,
        1.5608547925949097,
        1.5179988145828247,
        1.5747989416122437,
        1.6014372110366821,
        1.6061846017837524,
        1.620341181755066,
        1.6083247661590576,
        1.5896557569503784,
        1.5364470481872559,
        1.6156834363937378,
        1.4952913522720337,
        1.3767218589782715,
        1.480371117591858,
        1.4717371463775635,
        1.3485805988311768,
        1.4527006149291992,
        1.2449764013290405,
        1.3080817461013794,
        1.2660586833953857,
        1.3827165365219116,
        1.3059104681015015,
        1.364537000656128,
        1.3448212146759033,
        1.4717391729354858,
        1.4967162609100342,
        1.4751700162887573,
        1.344270944595337,
        1.4614684581756592,
        1.3942677974700928,
        1.4073970317840576,
        1.324061393737793,
        1.4183320999145508,
        1.2691106796264648,
        1.410280704498291,
        1.2375526428222656,
        1.294121503829956,
        1.4368946552276611,
        1.372113823890686,
        1.36270272731781,
        1.2945747375488281,
        1.1258033514022827,
        1.2100613117218018,
        1.2521170377731323,
        1.291763186454773,
        1.2463390827178955,
        1.1621789932250977,
        1.2186635732650757,
        1.2860498428344727,
        1.353494644165039,
        1.244316577911377,
        1.2321255207061768,
        1.2793956995010376,
        1.0379314422607422,
        1.1159526109695435,
        1.1665548086166382,
        1.2058650255203247,
        1.105823040008545,
        1.3641180992126465,
        1.1764508485794067,
        1.086543083190918,
        1.3595792055130005,
        1.208926796913147,
        1.194172978401184,
        1.1951991319656372,
        0.933534562587738,
        1.0625826120376587,
        0.976327121257782,
        1.0945439338684082,
        0.9780505895614624,
        1.0105443000793457,
        0.8468376398086548,
        1.1082067489624023
      ],
      "probe": {
        "accuracy": 0.671875,
        "confusion_matrix": [
          [
            23,
            9
          ],
          [
            12,
            20
          ]
        ],
        "macro_f1": 0.6711524345485687,
        "train_accuracy": 0.9010416666666666,
        "train_macro_f1": 0.9009745107087598
      },
      "retrieval": {
        "map_at_r": 0.45269226309278077,
        "mean_relevant_items": 96.0,
        "precision_at_1": 0.609375
      },
      "space": {
        "drift_to_gap_ratio": 0.34889536932963033,
        "signal_to_noise_ratio": 0.37564910450110184,
        "test_within_class_radius": 0.7787045268077906,
        "train_centroid_gap": 0.5659505126881166,
        "train_test_centroid_drift": 0.19745751314661408,
        "train_within_class_radius": 0.7278890093055281
      },
      "triplet_loss": 0.27236216169146626
    },
    "group_finetuned:sentence-transformers/paraphrase-MiniLM-L3-v2": {
      "dimensions": 384,
      "group_loss": 0.7095278478562621,
      "initial_group_loss": 1.0122567041741284,
      "initial_probe": {
        "accuracy": 0.78125,
        "confusion_matrix": [
          [
            25,
            7
          ],
          [
            7,
            25
          ]
        ],
        "macro_f1": 0.78125,
        "train_accuracy": 0.875,
        "train_macro_f1": 0.8749864351600651
      },
      "initial_retrieval": {
        "map_at_r": 0.30303404557635916,
        "mean_relevant_items": 96.0,
        "precision_at_1": 0.546875
      },
      "initial_space": {
        "drift_to_gap_ratio": 0.837125212693542,
        "signal_to_noise_ratio": 0.11641856857046612,
        "test_within_class_radius": 0.8372645325001753,
        "train_centroid_gap": 0.19390105222162995,
        "train_test_centroid_drift": 0.16231945958253358,
        "train_within_class_radius": 0.8282863723304836
      },
      "initial_triplet_loss": 0.4912109756862438,
      "objective_history": [
        1.000551462173462,
        0.9552038908004761,
        1.0493474006652832,
        1.0685145854949951,
        0.9270983934402466,
        0.9345880746841431,
        0.8880296945571899,
        1.0144333839416504,
        1.059633493423462,
        1.0182640552520752,
        1.007779836654663,
        1.0782394409179688,
        0.9569673538208008,
        1.0010559558868408,
        1.0132815837860107,
        1.056800127029419,
        0.9650184512138367,
        1.0697658061981201,
        0.9487937688827515,
        0.9728663563728333,
        1.0608782768249512,
        1.0151715278625488,
        0.9726251363754272,
        0.9263323545455933,
        0.8185420036315918,
        0.8110125660896301,
        0.8789188861846924,
        0.8747724294662476,
        0.8236299753189087,
        0.7907884120941162,
        0.8042117357254028,
        0.914880096912384,
        0.942398190498352,
        0.877598762512207,
        0.8977960348129272,
        0.9761061668395996,
        0.8351340293884277,
        0.8631042242050171,
        0.9070806503295898,
        0.9060803651809692,
        0.8629865646362305,
        0.9759806990623474,
        0.8406524658203125,
        0.8786377906799316,
        0.9611992239952087,
        0.9314953088760376,
        0.8670775890350342,
        0.8603169322013855,
        0.7267376780509949,
        0.7665780782699585,
        0.7756977081298828,
        0.8169610500335693,
        0.7371318340301514,
        0.7836853265762329,
        0.7639206051826477,
        0.8078534603118896,
        0.8626539707183838,
        0.8314379453659058,
        0.8202542066574097,
        0.9215904474258423,
        0.7296836376190186,
        0.7927248477935791,
        0.7936862707138062,
        0.8189562559127808,
        0.7578082084655762,
        0.9515938758850098,
        0.7878028154373169,
        0.8186602592468262,
        0.9413717985153198,
        0.866593599319458,
        0.8270783424377441,
        0.7885431051254272,
        0.6373449563980103,
        0.7276067137718201,
        0.6978336572647095,
        0.7327266931533813,
        0.6726897954940796,
        0.6921185255050659,
        0.6872107982635498,
        0.77094566822052
      ],
      "probe": {
        "accuracy": 0.65625,
        "confusion_matrix": [
          [
            23,
            9
          ],
          [
            13,
            19
          ]
        ],
        "macro_f1": 0.6549019607843137,
        "train_accuracy": 0.8958333333333334,
        "train_macro_f1": 0.8957315086347344
      },
      "retrieval": {
        "map_at_r": 0.4133537237799938,
        "mean_relevant_items": 96.0,
        "precision_at_1": 0.640625
      },
      "space": {
        "drift_to_gap_ratio": 0.3877949245628525,
        "signal_to_noise_ratio": 0.3020796828070653,
        "test_within_class_radius": 0.5558205579741047,
        "train_centroid_gap": 0.32815128583942516,
        "train_test_centroid_drift": 0.12725540313730294,
        "train_within_class_radius": 0.5304864812484288
      },
      "triplet_loss": 0.41105303520611325
    },
    "hybrid_finetuned:sentence-transformers/paraphrase-MiniLM-L3-v2": {
      "dimensions": 384,
      "group_loss": 0.5853357848468242,
      "initial_group_loss": 1.0122567041741284,
      "initial_probe": {
        "accuracy": 0.78125,
        "confusion_matrix": [
          [
            25,
            7
          ],
          [
            7,
            25
          ]
        ],
        "macro_f1": 0.78125,
        "train_accuracy": 0.875,
        "train_macro_f1": 0.8749864351600651
      },
      "initial_retrieval": {
        "map_at_r": 0.30303404557635916,
        "mean_relevant_items": 96.0,
        "precision_at_1": 0.546875
      },
      "initial_space": {
        "drift_to_gap_ratio": 0.837125212693542,
        "signal_to_noise_ratio": 0.11641856857046612,
        "test_within_class_radius": 0.8372645325001753,
        "train_centroid_gap": 0.19390105222162995,
        "train_test_centroid_drift": 0.16231945958253358,
        "train_within_class_radius": 0.8282863723304836
      },
      "initial_triplet_loss": 0.4912109756862438,
      "objective_history": [
        1.4647759199142456,
        1.4119608402252197,
        1.4869263172149658,
        1.489518165588379,
        1.428166389465332,
        1.3448567390441895,
        1.4397642612457275,
        1.4228909015655518,
        1.5224778652191162,
        1.5029046535491943,
        1.5355631113052368,
        1.5699141025543213,
        1.5375245809555054,
        1.5520833730697632,
        1.578855276107788,
        1.5412760972976685,
        1.4916024208068848,
        1.598122000694275,
        1.4371638298034668,
        1.3287441730499268,
        1.4250984191894531,
        1.4444619417190552,
        1.3247495889663696,
        1.400924801826477,
        1.2008335590362549,
        1.2546415328979492,
        1.2441333532333374,
        1.3334102630615234,
        1.2569537162780762,
        1.2998725175857544,
        1.300552248954773,
        1.4212450981140137,
        1.4518193006515503,
        1.4515939950942993,
        1.3269693851470947,
        1.4151842594146729,
        1.328235149383545,
        1.4125208854675293,
        1.2611991167068481,
        1.3470920324325562,
        1.252314567565918,
        1.386909008026123,
        1.2576391696929932,
        1.248476266860962,
        1.451650619506836,
        1.3040879964828491,
        1.2910817861557007,
        1.2657222747802734,
        1.1039142608642578,
        1.1266214847564697,
        1.2591688632965088,
        1.2401034832000732,
        1.1659901142120361,
        1.1291290521621704,
        1.2190145254135132,
        1.2753325700759888,
        1.340329885482788,
        1.1944727897644043,
        1.1866542100906372,
        1.189415454864502,
        1.0106167793273926,
        1.0811500549316406,
        1.118047833442688,
        1.1532456874847412,
        1.0452145338058472,
        1.3212733268737793,
        1.141806960105896,
        1.0666842460632324,
        1.3215421438217163,
        1.1528798341751099,
        1.1492576599121094,
        1.1364705562591553,
        0.8953170776367188,
        1.0601770877838135,
        0.9153510332107544,
        1.077638864517212,
        0.8227059245109558,
        1.006279468536377,
        0.8384002447128296,
        0.9653961658477783
      ],
      "probe": {
        "accuracy": 0.671875,
        "confusion_matrix": [
          [
            23,
            9
          ],
          [
            12,
            20
          ]
        ],
        "macro_f1": 0.6711524345485687,
        "train_accuracy": 0.9010416666666666,
        "train_macro_f1": 0.9009745107087598
      },
      "retrieval": {
        "map_at_r": 0.45278532976279046,
        "mean_relevant_items": 96.0,
        "precision_at_1": 0.625
      },
      "space": {
        "drift_to_gap_ratio": 0.3509927676558156,
        "signal_to_noise_ratio": 0.3783860700219476,
        "test_within_class_radius": 0.8090676862744126,
        "train_centroid_gap": 0.5917960662308969,
        "train_test_centroid_drift": 0.20771613917420684,
        "train_within_class_radius": 0.7549329816058052
      },
      "triplet_loss": 0.26140402510469357
    },
    "hybrid_radius_finetuned:sentence-transformers/paraphrase-MiniLM-L3-v2": {
      "dimensions": 384,
      "group_loss": 0.6472017315382097,
      "initial_group_loss": 1.0122567041741284,
      "initial_probe": {
        "accuracy": 0.78125,
        "confusion_matrix": [
          [
            25,
            7
          ],
          [
            7,
            25
          ]
        ],
        "macro_f1": 0.78125,
        "train_accuracy": 0.875,
        "train_macro_f1": 0.8749864351600651
      },
      "initial_retrieval": {
        "map_at_r": 0.30303404557635916,
        "mean_relevant_items": 96.0,
        "precision_at_1": 0.546875
      },
      "initial_space": {
        "drift_to_gap_ratio": 0.837125212693542,
        "signal_to_noise_ratio": 0.11641856857046612,
        "test_within_class_radius": 0.8372645325001753,
        "train_centroid_gap": 0.19390105222162995,
        "train_test_centroid_drift": 0.16231945958253358,
        "train_within_class_radius": 0.8282863723304836
      },
      "initial_triplet_loss": 0.4912109756862438,
      "objective_history": [
        1.5385818481445312,
        1.4620119333267212,
        1.5445010662078857,
        1.533861756324768,
        1.4584020376205444,
        1.3718804121017456,
        1.463091254234314,
        1.4950649738311768,
        1.556779384613037,
        1.541015386581421,
        1.5736826658248901,
        1.6033048629760742,
        1.6023211479187012,
        1.6029161214828491,
        1.6269338130950928,
        1.5764820575714111,
        1.5168814659118652,
        1.6160366535186768,
        1.4967418909072876,
        1.414830207824707,
        1.4692392349243164,
        1.4692730903625488,
        1.3839820623397827,
        1.4275538921356201,
        1.2199714183807373,
        1.2704225778579712,
        1.2893096208572388,
        1.3656094074249268,
        1.318389892578125,
        1.3493146896362305,
        1.3457335233688354,
        1.446967363357544,
        1.5089659690856934,
        1.4982514381408691,
        1.3579152822494507,
        1.4785372018814087,
        1.392505168914795,
        1.4309735298156738,
        1.3000723123550415,
        1.38723886013031,
        1.2484028339385986,
        1.434699296951294,
        1.2389470338821411,
        1.281969666481018,
        1.4585905075073242,
        1.3481276035308838,
        1.322553038597107,
        1.3121317625045776,
        1.1478190422058105,
        1.2307981252670288,
        1.2535414695739746,
        1.2950061559677124,
        1.2153229713439941,
        1.1935670375823975,
        1.2169276475906372,
        1.3726688623428345,
        1.3749998807907104,
        1.2382670640945435,
        1.2327961921691895,
        1.2792378664016724,
        1.078133463859558,
        1.181828260421753,
        1.202505350112915,
        1.2342329025268555,
        1.1504807472229004,
        1.358333706855774,
        1.1892837285995483,
        1.1530389785766602,
        1.3545829057693481,
        1.2365648746490479,
        1.2811501026153564,
        1.2828232049942017,
        1.0008323192596436,
        1.116625189781189,
        1.062372088432312,
        1.1950229406356812,
        0.9909986853599548,
        1.0483801364898682,
        0.9684665203094482,
        1.1669518947601318
      ],
      "probe": {
        "accuracy": 0.625,
        "confusion_matrix": [
          [
            22,
            10
          ],
          [
            14,
            18
          ]
        ],
        "macro_f1": 0.6235294117647059,
        "train_accuracy": 0.9010416666666666,
        "train_macro_f1": 0.900909955181312
      },
      "retrieval": {
        "map_at_r": 0.4325648993423451,
        "mean_relevant_items": 96.0,
        "precision_at_1": 0.625
      },
      "space": {
        "drift_to_gap_ratio": 0.3612315750763974,
        "signal_to_noise_ratio": 0.3502574476020307,
        "test_within_class_radius": 0.6797057740934647,
        "train_centroid_gap": 0.46269368635950886,
        "train_test_centroid_drift": 0.16713956910155,
        "train_within_class_radius": 0.6413044985709739
      },
      "triplet_loss": 0.3144096295018662
    },
    "hybrid_xbm_finetuned:sentence-transformers/paraphrase-MiniLM-L3-v2": {
      "dimensions": 384,
      "group_loss": 0.5983599188239199,
      "initial_group_loss": 1.0122567041741284,
      "initial_probe": {
        "accuracy": 0.78125,
        "confusion_matrix": [
          [
            25,
            7
          ],
          [
            7,
            25
          ]
        ],
        "macro_f1": 0.78125,
        "train_accuracy": 0.875,
        "train_macro_f1": 0.8749864351600651
      },
      "initial_retrieval": {
        "map_at_r": 0.30303404557635916,
        "mean_relevant_items": 96.0,
        "precision_at_1": 0.546875
      },
      "initial_space": {
        "drift_to_gap_ratio": 0.837125212693542,
        "signal_to_noise_ratio": 0.11641856857046612,
        "test_within_class_radius": 0.8372645325001753,
        "train_centroid_gap": 0.19390105222162995,
        "train_test_centroid_drift": 0.16231945958253358,
        "train_within_class_radius": 0.8282863723304836
      },
      "initial_triplet_loss": 0.4912109756862438,
      "objective_history": [
        1.4811406135559082,
        1.4201923608779907,
        1.485090732574463,
        1.5006157159805298,
        1.5603766441345215,
        1.4622681140899658,
        1.4196906089782715,
        1.457587480545044,
        1.4893847703933716,
        1.5184239149093628,
        1.5369336605072021,
        1.5724384784698486,
        1.5531868934631348,
        1.5636377334594727,
        1.6018335819244385,
        1.5447595119476318,
        1.491436243057251,
        1.5931392908096313,
        1.4819252490997314,
        1.3439656496047974,
        1.4641448259353638,
        1.4308720827102661,
        1.3316713571548462,
        1.37205171585083,
        1.1835380792617798,
        1.2994155883789062,
        1.2326325178146362,
        1.3266600370407104,
        1.2440204620361328,
        1.3147907257080078,
        1.2597309350967407,
        1.398696780204773,
        1.4728851318359375,
        1.4550974369049072,
        1.3326184749603271,
        1.4188697338104248,
        1.345633864402771,
        1.4024183750152588,
        1.2560739517211914,
        1.3193824291229248,
        1.2295756340026855,
        1.3844311237335205,
        1.221190333366394,
        1.2248388528823853,
        1.4005317687988281,
        1.348724365234375,
        1.3247079849243164,
        1.2760701179504395,
        1.1207953691482544,
        1.198588252067566,
        1.205273985862732,
        1.1996392011642456,
        1.2310727834701538,
        1.149365782737732,
        1.1925880908966064,
        1.2885386943817139,
        1.3221070766448975,
        1.1751611232757568,
        1.2153820991516113,
        1.2197222709655762,
        1.003505825996399,
        1.0908695459365845,
        1.1228641271591187,
        1.164480447769165,
        1.0928499698638916,
        1.3169385194778442,
        1.146299123764038,
        1.0844852924346924,
        1.291588306427002,
        1.2026588916778564,
        1.1809462308883667,
        1.1781471967697144,
        0.8614163398742676,
        1.0170176029205322,
        0.9519144296646118,
        1.0603117942810059,
        0.8916388750076294,
        0.9434807300567627,
        0.8210766315460205,
        0.9731858968734741
      ],
      "probe": {
        "accuracy": 0.6875,
        "confusion_matrix": [
          [
            24,
            8
          ],
          [
            12,
            20
          ]
        ],
        "macro_f1": 0.6862745098039216,
        "train_accuracy": 0.9114583333333334,
        "train_macro_f1": 0.9114367114367115
      },
      "retrieval": {
        "map_at_r": 0.4465971506170376,
        "mean_relevant_items": 96.0,
        "precision_at_1": 0.578125
      },
      "space": {
        "drift_to_gap_ratio": 0.36677375119087036,
        "signal_to_noise_ratio": 0.35452978401423396,
        "test_within_class_radius": 0.8369253171803663,
        "train_centroid_gap": 0.5754552670280668,
        "train_test_centroid_drift": 0.21106188693042804,
        "train_within_class_radius": 0.786225382634922
      },
      "triplet_loss": 0.26333710043020764
    },
    "triplet_finetuned:sentence-transformers/paraphrase-MiniLM-L3-v2": {
      "dimensions": 384,
      "group_loss": 0.8537190540994727,
      "initial_group_loss": 1.0122567041741284,
      "initial_probe": {
        "accuracy": 0.78125,
        "confusion_matrix": [
          [
            25,
            7
          ],
          [
            7,
            25
          ]
        ],
        "macro_f1": 0.78125,
        "train_accuracy": 0.875,
        "train_macro_f1": 0.8749864351600651
      },
      "initial_retrieval": {
        "map_at_r": 0.30303404557635916,
        "mean_relevant_items": 96.0,
        "precision_at_1": 0.546875
      },
      "initial_space": {
        "drift_to_gap_ratio": 0.837125212693542,
        "signal_to_noise_ratio": 0.11641856857046612,
        "test_within_class_radius": 0.8372645325001753,
        "train_centroid_gap": 0.19390105222162995,
        "train_test_centroid_drift": 0.16231945958253358,
        "train_within_class_radius": 0.8282863723304836
      },
      "initial_triplet_loss": 0.4912109756862438,
      "objective_history": [
        0.46499738097190857,
        0.4333166182041168,
        0.48146364092826843,
        0.44527101516723633,
        0.4853450357913971,
        0.3987317383289337,
        0.5031665563583374,
        0.43053609132766724,
        0.4629644453525543,
        0.5358735918998718,
        0.569908082485199,
        0.521822452545166,
        0.5772562026977539,
        0.5638846755027771,
        0.5733330845832825,
        0.43867483735084534,
        0.5061578154563904,
        0.5262032747268677,
        0.5117390751838684,
        0.36966291069984436,
        0.3554324805736542,
        0.34324952960014343,
        0.3664969503879547,
        0.42971011996269226,
        0.3390584886074066,
        0.46178969740867615,
        0.3595387041568756,
        0.4265407621860504,
        0.45429617166519165,
        0.5310344099998474,
        0.4831486642360687,
        0.5114851593971252,
        0.5268212556838989,
        0.5708263516426086,
        0.40517258644104004,
        0.42032986879348755,
        0.46533116698265076,
        0.49742451310157776,
        0.3342934846878052,
        0.32498136162757874,
        0.2671024799346924,
        0.3717817962169647,
        0.32260140776634216,
        0.33466842770576477,
        0.3624096214771271,
        0.35355719923973083,
        0.39849498867988586,
        0.3502284586429596,
        0.46207085251808167,
        0.41170841455459595,
        0.4477100372314453,
        0.4613739550113678,
        0.48933807015419006,
        0.34229645133018494,
        0.42921486496925354,
        0.42182406783103943,
        0.4368138015270233,
        0.3300846219062805,
        0.270367830991745,
        0.23595571517944336,
        0.29202720522880554,
        0.33013373613357544,
        0.33652544021606445,
        0.2675078213214874,
        0.2968253493309021,
        0.3414950966835022,
        0.3323862850666046,
        0.3279428482055664,
        0.30304479598999023,
        0.3858661651611328,
        0.3900579512119293,
        0.41424664855003357,
        0.28178641200065613,
        0.3310122489929199,
        0.30088305473327637,
        0.37621304392814636,
        0.2935446500778198,
        0.23963265120983124,
        0.1796189844608307,
        0.3005654513835907
      ],
      "probe": {
        "accuracy": 0.703125,
        "confusion_matrix": [
          [
            23,
            9
          ],
          [
            10,
            22
          ]
        ],
        "macro_f1": 0.703052503052503,
        "train_accuracy": 0.890625,
        "train_macro_f1": 0.8904794241477658
      },
      "retrieval": {
        "map_at_r": 0.35472180909424406,
        "mean_relevant_items": 96.0,
        "precision_at_1": 0.59375
      },
      "space": {
        "drift_to_gap_ratio": 0.5128501077553544,
        "signal_to_noise_ratio": 0.20185409576245059,
        "test_within_class_radius": 0.9608741081005514,
        "train_centroid_gap": 0.3841820780174887,
        "train_test_centroid_drift": 0.1970278201089451,
        "train_within_class_radius": 0.9423920929955537
      },
      "triplet_loss": 0.24729322910418614
    }
  },
  "name": "sentence-transformer-training",
  "test_examples": 64,
  "train_examples": 192,
  "triplets": 192
}
